LICENSE.txt
MANIFEST.in
README.md
pyproject.toml
setup.cfg
setup.py
dssystem/method.py
dssystem/test.py
dssystem.egg-info/PKG-INFO
dssystem.egg-info/SOURCES.txt
dssystem.egg-info/dependency_links.txt
dssystem.egg-info/requires.txt
dssystem.egg-info/top_level.txt