Metadata-Version: 2.1
Name: dssystem
Version: 0.1.5
Summary: The basic concept SAW method is to find the sum of the weighted performance rating for each alternative on all attributes. SAW method requires a process of normalizing the decision matrix (X) to a scale that can be compared with all the ratings of existing alternatives.
Home-page: UNKNOWN
Author: Rafi Mochamad Fahreza
Author-email: prokodingproject@gmail.com
License: UNKNOWN
Keywords: algorithm,dss,decision
Platform: UNKNOWN
Classifier: Development Status :: 3 - Alpha
Classifier: Intended Audience :: Developers
Classifier: Topic :: Scientific/Engineering :: Artificial Intelligence 
Classifier: Programming Language :: Python :: 3
Classifier: Programming Language :: Python :: 3.6
Classifier: Programming Language :: Python :: 3.7
Classifier: Programming Language :: Python :: 3.8
Requires-Python: >=3
